{
  "access": [
    "director-access-events"
  ],
  "additions": [
    "recent"
  ],
  "addons": [
    "addons-common"
  ],
  "affinity": [
    "vm-anti-affinity"
  ],
  "agent": [
    "agent-cpi-interactions"
  ],
  "anti": [
    "vm-anti-affinity"
  ],
  "api": [
    "cpi-api-v1",
    "director-api-v1",
    "openstack-keystonev2"
  ],
  "arp": [
    "flush-arp"
  ],
  "automatic": [
    "resurrector"
  ],
  "availability": [
    "azs"
  ],
  "aws": [
    "aws-cpi",
    "deploy-microbosh-to-aws",
    "init-aws",
    "setup-aws"
  ],
  "azs": [
    "azs"
  ],
  "azure": [
    "azure-cpi",
    "azure-resources",
    "init-azure"
  ],
  "backup": [
    "director-backup"
  ],
  "basic": [
    "basic-workflow",
    "workflow"
  ],
  "basics": [
    "deployment-basics"
  ],
  "blobstore": [
    "director-configure-blobstore",
    "s3-release-blobstore"
  ],
  "bootstrapping": [
    "bootstrap"
  ],
  "bosh": [
    "about",
    "bosh-cli",
    "bosh-components",
    "bosh-lite",
    "deploy-with-bosh",
    "design",
    "director-backup",
    "disaster-recovery",
    "init-aws",
    "init-azure",
    "init-openstack",
    "init-softlayer",
    "init-vcloud",
    "init-vsphere",
    "install-bosh-init",
    "migrate-to-bosh-init",
    "packages",
    "problems",
    "sample-manifest",
    "setup-aws",
    "setup-openstack",
    "setup-vsphere",
    "understanding-bosh",
    "using-bosh-init",
    "vm-struct",
    "workflow"
  ],
  "building": [
    "build-cpi",
    "build-stemcell"
  ],
  "certificate": [
    "director-certs"
  ],
  "certificates": [
    "trusted-certs"
  ],
  "check": [
    "cck"
  ],
  "class": [
    "azs"
  ],
  "cli": [
    "cli-v2",
    "migrate-to-bosh-init",
    "sysadmin-commands"
  ],
  "cloud": [
    "cck",
    "cloud-config"
  ],
  "command": [
    "bosh-cli"
  ],
  "commands": [
    "sysadmin-commands"
  ],
  "common": [
    "addons-common"
  ],
  "compiled": [
    "compiled-releases"
  ],
  "compilers": [
    "remove-dev-tools"
  ],
  "components": [
    "bosh-components"
  ],
  "config": [
    "cloud-config",
    "runtime-config"
  ],
  "configuration": [
    "director-certs",
    "openstack-registry",
    "vm-config"
  ],
  "configuring": [
    "hm-config"
  ],
  "connecting": [
    "director-configure-blobstore",
    "director-configure-db"
  ],
  "cpi": [
    "agent-cpi-interactions",
    "aws-cpi",
    "azure-cpi",
    "build-cpi",
    "cpi-api-v1",
    "google-cpi",
    "openstack-cpi",
    "rackhd-cpi",
    "softlayer-cpi",
    "vcloud-cpi",
    "virtualbox-cpi",
    "vsphere-cpi",
    "warden-cpi"
  ],
  "creating": [
    "aws-iam-users",
    "azure-resources",
    "create-micro-manifest",
    "create-release",
    "packages"
  ],
  "customizing": [
    "persistent-disk-fs"
  ],
  "database": [
    "director-configure-db"
  ],
  "datastore": [
    "vsphere-migrate-datastores"
  ],
  "deploy": [
    "post-deploy"
  ],
  "deploying": [
    "deploy-microbosh-to-aws",
    "deploy-microbosh-to-openstack",
    "deploy-microbosh-to-vsphere",
    "deploy-microbosh",
    "deploy-with-bosh",
    "deploy_microbosh_to_vcloud",
    "deploying-step-by-step",
    "deploying"
  ],
  "deployment": [
    "create-micro-manifest",
    "deployment-basics",
    "deployment-manifest",
    "deployment",
    "director-backup",
    "sample-manifest"
  ],
  "design": [
    "design"
  ],
  "development": [
    "remove-dev-tools"
  ],
  "director": [
    "director-api-v1",
    "director-backup",
    "director-certs",
    "director-configure-blobstore",
    "director-configure-db",
    "director-tasks",
    "director-users"
  ],
  "disaster": [
    "disaster-recovery"
  ],
  "disk": [
    "persistent-disk-fs",
    "snapshots"
  ],
  "disks": [
    "persistent-disks"
  ],
  "distributed": [
    "deploy-with-bosh"
  ],
  "drain": [
    "drain"
  ],
  "drs": [
    "vsphere-vmotion-support"
  ],
  "endpoints": [
    "openstack-self-signed-endpoints"
  ],
  "environment": [
    "bootstrap",
    "init-aws",
    "init-azure",
    "init-openstack",
    "init-softlayer",
    "init-vcloud",
    "init-vsphere",
    "init"
  ],
  "esxi": [
    "vsphere-esxi-host-failure"
  ],
  "event": [
    "director-access-events"
  ],
  "events": [
    "events"
  ],
  "explicit": [
    "flush-arp"
  ],
  "extended": [
    "openstack-registry"
  ],
  "external": [
    "director-configure-blobstore",
    "director-configure-db"
  ],
  "failure": [
    "vsphere-esxi-host-failure"
  ],
  "fault": [
    "vsphere-network-partition"
  ],
  "filesystem": [
    "persistent-disk-fs"
  ],
  "flushing": [
    "flush-arp"
  ],
  "garden": [
    "warden-cpi"
  ],
  "google": [
    "google-cpi"
  ],
  "groups": [
    "migrated-from"
  ],
  "ha": [
    "vsphere-ha"
  ],
  "health": [
    "hm-config"
  ],
  "homed": [
    "openstack-multiple-networks"
  ],
  "host": [
    "vsphere-esxi-host-failure"
  ],
  "human": [
    "openstack-human-readable-vm-names"
  ],
  "iam": [
    "aws-iam-instance-profiles",
    "aws-iam-users"
  ],
  "index": [
    "index"
  ],
  "init": [
    "install-bosh-init",
    "migrate-to-bosh-init",
    "using-bosh-init"
  ],
  "initializing": [
    "init-aws",
    "init-azure",
    "init-openstack",
    "init-softlayer",
    "init-vcloud",
    "init-vsphere",
    "init"
  ],
  "install": [
    "install-bosh-init"
  ],
  "instance": [
    "aws-iam-instance-profiles",
    "aws-instance-storage",
    "instance-metadata",
    "migrated-from"
  ],
  "integration": [
    "director-users-uaa"
  ],
  "interactions": [
    "agent-cpi-interactions"
  ],
  "interface": [
    "bosh-cli"
  ],
  "job": [
    "job-lifecycle"
  ],
  "jobs": [
    "jobs"
  ],
  "keystone": [
    "openstack-keystonev2"
  ],
  "lifecycle": [
    "job-lifecycle"
  ],
  "light": [
    "openstack-light-stemcells"
  ],
  "line": [
    "bosh-cli"
  ],
  "link": [
    "links-properties"
  ],
  "linking": [
    "links-manual"
  ],
  "links": [
    "links"
  ],
  "lite": [
    "bosh-lite"
  ],
  "location": [
    "job-logs"
  ],
  "locations": [
    "vm-config"
  ],
  "logging": [
    "director-access-events"
  ],
  "logs": [
    "job-logs"
  ],
  "management": [
    "director-users"
  ],
  "managing": [
    "managing-releases",
    "managing-stemcells"
  ],
  "manifest": [
    "create-micro-manifest",
    "deployment-manifest",
    "manifest-v2",
    "sample-manifest"
  ],
  "manual": [
    "cck",
    "links-manual"
  ],
  "metadata": [
    "instance-metadata"
  ],
  "micro": [
    "migrate-to-bosh-init"
  ],
  "microbosh": [
    "create-micro-manifest",
    "deploy-microbosh-to-aws",
    "deploy-microbosh-to-openstack",
    "deploy-microbosh-to-vsphere",
    "deploy-microbosh",
    "deploy_microbosh_to_vcloud"
  ],
  "migrating": [
    "migrate-to-bosh-init",
    "migrated-from",
    "vsphere-migrate-datastores"
  ],
  "monit": [
    "vm-monit"
  ],
  "monitor": [
    "hm-config"
  ],
  "monitoring": [
    "monitoring",
    "vm-monit"
  ],
  "multi": [
    "openstack-multiple-networks"
  ],
  "names": [
    "openstack-human-readable-vm-names"
  ],
  "network": [
    "vsphere-network-partition"
  ],
  "networking": [
    "openstack-nova-networking"
  ],
  "networks": [
    "networks"
  ],
  "nova": [
    "openstack-nova-networking"
  ],
  "openstack": [
    "deploy-microbosh-to-openstack",
    "init-openstack",
    "openstack-cpi",
    "openstack-self-signed-endpoints",
    "setup-openstack"
  ],
  "orphaned": [
    "persistent-disks"
  ],
  "packages": [
    "packages"
  ],
  "partitioning": [
    "vsphere-network-partition"
  ],
  "permissions": [
    "director-users-uaa-perms"
  ],
  "persistent": [
    "persistent-disk-fs",
    "persistent-disks",
    "snapshots"
  ],
  "plugin": [
    "migrate-to-bosh-init"
  ],
  "post": [
    "post-deploy",
    "post-start"
  ],
  "postgres": [
    "director-configure-db"
  ],
  "pre": [
    "pre-start"
  ],
  "principles": [
    "design"
  ],
  "problems": [
    "problems"
  ],
  "process": [
    "vm-monit"
  ],
  "processes": [
    "scheduled-procs"
  ],
  "profiles": [
    "aws-iam-instance-profiles"
  ],
  "properties": [
    "links-properties"
  ],
  "rackhd": [
    "rackhd-cpi"
  ],
  "readable": [
    "openstack-human-readable-vm-names"
  ],
  "recent": [
    "recent"
  ],
  "recovery": [
    "disaster-recovery",
    "vsphere-esxi-host-failure",
    "vsphere-network-partition"
  ],
  "registry": [
    "openstack-registry"
  ],
  "release": [
    "create-release",
    "release",
    "s3-release-blobstore"
  ],
  "releases": [
    "compiled-releases",
    "managing-releases",
    "uploading-releases"
  ],
  "removal": [
    "remove-dev-tools"
  ],
  "renaming": [
    "migrated-from"
  ],
  "repair": [
    "cck",
    "resurrector"
  ],
  "resources": [
    "azure-resources"
  ],
  "restore": [
    "director-backup"
  ],
  "resurrector": [
    "resurrector"
  ],
  "runtime": [
    "runtime-config"
  ],
  "s3": [
    "s3-release-blobstore"
  ],
  "sample": [
    "sample-manifest"
  ],
  "scheduled": [
    "scheduled-procs"
  ],
  "schema": [
    "deployment-manifest",
    "manifest-v2"
  ],
  "script": [
    "drain",
    "post-deploy",
    "post-start",
    "pre-start"
  ],
  "setting": [
    "s3-release-blobstore",
    "setup-aws",
    "setup-openstack",
    "setup-vsphere"
  ],
  "signed": [
    "openstack-self-signed-endpoints"
  ],
  "snapshotting": [
    "snapshots"
  ],
  "softlayer": [
    "init-softlayer",
    "softlayer-cpi"
  ],
  "software": [
    "deploy-with-bosh"
  ],
  "solve": [
    "problems"
  ],
  "ssl": [
    "director-certs"
  ],
  "start": [
    "post-start",
    "pre-start"
  ],
  "stemcell": [
    "build-stemcell",
    "stemcell"
  ],
  "stemcells": [
    "managing-stemcells",
    "openstack-light-stemcells",
    "uploading-stemcells"
  ],
  "step": [
    "deploying-step-by-step"
  ],
  "storage": [
    "aws-instance-storage",
    "vsphere-vmotion-support"
  ],
  "structure": [
    "vm-struct"
  ],
  "support": [
    "vsphere-vmotion-support"
  ],
  "tasks": [
    "director-tasks"
  ],
  "terminology": [
    "terminology"
  ],
  "tips": [
    "tips"
  ],
  "tools": [
    "remove-dev-tools"
  ],
  "trusted": [
    "trusted-certs"
  ],
  "uaa": [
    "director-users-uaa-perms",
    "director-users-uaa"
  ],
  "understanding": [
    "understanding-bosh"
  ],
  "updates": [
    "recent"
  ],
  "uploading": [
    "uploading-releases",
    "uploading-stemcells"
  ],
  "user": [
    "director-users"
  ],
  "users": [
    "aws-iam-users"
  ],
  "uuids": [
    "openstack-human-readable-vm-names"
  ],
  "v1": [
    "cli-v2",
    "cpi-api-v1",
    "director-api-v1"
  ],
  "v2": [
    "cli-v2",
    "manifest-v2",
    "openstack-keystonev2"
  ],
  "validating": [
    "openstack-self-signed-endpoints"
  ],
  "vcloud": [
    "deploy_microbosh_to_vcloud",
    "init-vcloud",
    "vcloud-cpi"
  ],
  "virtualbox": [
    "virtualbox-cpi"
  ],
  "vm": [
    "openstack-human-readable-vm-names",
    "vm-anti-affinity",
    "vm-config",
    "vm-struct"
  ],
  "vmotion": [
    "vsphere-vmotion-support"
  ],
  "vms": [
    "openstack-multiple-networks"
  ],
  "vsphere": [
    "deploy-microbosh-to-vsphere",
    "init-vsphere",
    "setup-vsphere",
    "vsphere-cpi",
    "vsphere-ha",
    "vsphere-network-partition"
  ],
  "warden": [
    "warden-cpi"
  ],
  "workflow": [
    "basic-workflow",
    "workflow"
  ],
  "zones": [
    "azs"
  ]
}